healing_scattering_image/__init__.py
healing_scattering_image/_version.py
healing_scattering_image/example_test.py
healing_scattering_image/heal_scatter_image.py
healing_scattering_image/oneD_intensity.py
healing_scattering_image/example_data/example_1.npz
healing_scattering_image/tests/__init__.py
healing_scattering_image/tests/conftest.py
healing_scattering_image/tests/test_examples.py
healing_scattering_image-0.1.1.dist-info/METADATA
healing_scattering_image-0.1.1.dist-info/RECORD
healing_scattering_image-0.1.1.dist-info/WHEEL
healing_scattering_image-0.1.1.dist-info/entry_points.txt
healing_scattering_image-0.1.1.dist-info/top_level.txt
