Metadata-Version: 2.1
Name: healing-scattering-image
Version: 0.1.1
Summary: judge the structrual symmetry and heal the defects  within scattering image
Home-page: https://github.com/ligerliu/healing_scattering_image
Author: jiliang
Author-email: ligerliu@gmail.com
License: BSD (3-clause)
Platform: UNKNOWN
Classifier: Development Status :: 2 - Pre-Alpha
Classifier: Natural Language :: English
Classifier: Programming Language :: Python :: 3
Requires-Dist: numpy
Requires-Dist: scipy
Requires-Dist: scikit-image
Requires-Dist: matplotlib
